README
setup.py
pwl_maker/__init__.py
pwl_maker/signal.py
pwl_maker.egg-info/PKG-INFO
pwl_maker.egg-info/SOURCES.txt
pwl_maker.egg-info/dependency_links.txt
pwl_maker.egg-info/top_level.txt
tests/__init__.py
tests/signal_tests.py