Metadata-Version: 1.0
Name: pwl-maker
Version: 0.1.0
Summary: Utilities for creating LTSpice PWL files
Home-page: https://github.com/superlou/pwl-maker
Author: Louis Simons
Author-email: lousimons@gmail.com
License: GPLv3
Platform: UNKNOWN
